mutube/auth.py
mutube/channel.py
mutube/cli.py
mutube/config.py
mutube/rss.py
mutube/utils.py
mutube/video.py
mutube-0.1.2.dist-info/METADATA
mutube-0.1.2.dist-info/WHEEL
mutube-0.1.2.dist-info/entry_points.txt
mutube-0.1.2.dist-info/RECORD
