Metadata-Version: 2.4
Name: mutube
Version: 0.1.2
Summary: Open source 1of10/Viewstats alternative. Find out if a youtube video is a relative outlier.
Project-URL: Homepage, https://github.com/mutube-org/cli
Project-URL: Repository, https://github.com/mutube-org/cli
Project-URL: Issues, https://github.com/mutube-org/cli/issues
Requires-Python: >=3.13
Requires-Dist: build>=1.2.2.post1
Requires-Dist: click>=8.1.7
Requires-Dist: google-api-python-client>=2.168.0
Requires-Dist: google-auth-oauthlib>=1.2.2
Requires-Dist: rich>=14.0.0
Requires-Dist: twine>=6.1.0
Requires-Dist: xmltodict>=0.14.2
